{
  "ui_language": "sl",
  "generated_title": "Izraelska vojska v Gazi ubila Mohameda Odeha, novega poveljnika Hamasa",
  "event_overview": {
    "title": "Izraelska vojska v Gazi ubila Mohameda Odeha, novega poveljnika Hamasa",
    "summary": "Izraelske obrambne sile so v ciljno usmerjenem torkovem napadu v Gazi eliminirale Mohameda Odeha, ki je pred kratkim prevzel vodenje Brigade Izedina al Kasama, vojaškega krila gibanja Hamas. Izraelski premier Benjamin Netanjahu in obrambni minister Izrael Kac sta Odeha označila za enega ključnih snovalcev napadov na Izrael 7. oktobra 2023, v katerih je bilo ubitih približno 1200 ljudi.\n\nNapad je poleg Odeha zahteval še pet drugih žrtev, med katerimi sta bila po navedbah družine tudi njegova žena in sin. Medtem ko Izrael poudarja svojo zavezo k uničenju vseh voditeljev Hamasa, palestinska stran opozarja, da uboji ne bodo ustavili upora. Hamas smrti svojega poveljnika uradno še ni potrdil, viri blizu gibanja pa navajajo, da je bil Odeh morda zadnji preostali član višjega vodstvenega sveta oboroženega krila.",
    "key_points": [
      "Mohamed Odeh je bil ubit v torkovem napadu v Gazi, le nekaj dni po prevzemu funkcije.",
      "Izraelski vrh ga obtožuje vodenja obveščevalne divizije med napadom 7. oktobra 2023.",
      "V napadu je bilo skupno ubitih šest ljudi, vključno z Odehovo družino.",
      "Odeh je nasledil Izedina al Hadada, ki je bil ubit v podobnem napadu 15. maja.",
      "Hamas uradno še ni potrdil smrti poveljnika, sorodniki pa napovedujejo nadaljevanje boja.",
      "Izrael napoveduje nadaljevanje eliminacije vseh vpletenih v lanske napade.",
      "Obrambni minister Kac je omenil načrte za prihodnjo 'prostovoljno selitev' Palestincev iz Gaze."
    ],
    "timeline": [
      {
        "date": "7. oktober 2023",
        "description": "Hamas izvede obsežen napad na jug Izraela; Odeh naj bi bil eden od snovalcev."
      },
      {
        "date": "15. maj 2024",
        "description": "V izraelskem napadu ubit prejšnji poveljnik vojaškega krila Izedin al Hadad."
      },
      {
        "date": "Maj 2024 (nekaj dni pred ubojem)",
        "description": "Mohamed Odeh prevzame vodenje Brigade Izedina al Kasama."
      },
      {
        "date": "Torek, 26. maj 2024",
        "description": "Izraelska vojska izvede ciljno usmerjen napad, v katerem je ubit Odeh s svojo družino."
      },
      {
        "date": "Sreda, 27. maj 2024",
        "description": "Izraelski obrambni minister Izrael Kac javno potrdi eliminacijo Odeha."
      }
    ]
  }
}